[
  {
    "type": "vehicle",
    "id": "pickup_eb",
    "name": "Extended Bed Pickup",
    "parts": [
      { "x": 0, "y": 0, "parts": [ "frame_vertical_2", "seat", "seatbelt", "controls", "dashboard" ] },
      { "x": 0, "y": 0, "parts": [ "vehicle_alarm", "stereo", "horn_car", "roof" ] },
      { "x": 0, "y": 1, "parts": [ "frame_vertical_2", "seat", "seatbelt", "roof" ] },
      { "x": 0, "y": 2, "parts": [ "frame_vertical", "door" ] },
      { "x": 0, "y": -1, "parts": [ "frame_vertical", "door" ] },
      { "x": 1, "y": 0, "parts": [ "frame_horizontal", "windshield" ] },
      { "x": 1, "y": 1, "parts": [ "frame_horizontal", "windshield" ] },
      { "x": 1, "y": 2, "parts": [ "frame_vertical", "windshield" ] },
      { "x": 1, "y": -1, "parts": [ "frame_vertical", "windshield" ] },
      { "x": 2, "y": 0, "parts": [ "frame_horizontal", "halfboard_horizontal", "engine_v8" ] },
      { "x": 2, "y": 0, "parts": [ "alternator_truck", "battery_car" ] },
      { "x": 2, "y": 1, "parts": [ "frame_horizontal", "halfboard_horizontal" ] },
      { "x": 2, "y": 2, "parts": [ "frame_ne", "halfboard_ne", "headlight" ] },
      { "x": 2, "y": 2, "parts": [ "wheel_mount_medium_steerable", "wheel" ] },
      { "x": 2, "y": -1, "parts": [ "frame_nw", "halfboard_nw", "headlight" ] },
      { "x": 2, "y": -1, "parts": [ "wheel_mount_medium_steerable", "wheel" ] },
      { "x": -1, "y": 0, "parts": [ "frame_vertical_2", "windshield", "roof" ] },
      { "x": -1, "y": 1, "parts": [ "frame_vertical_2", "windshield", "roof" ] },
      { "x": -1, "y": 2, "parts": [ "frame_vertical", "halfboard_vertical" ] },
      { "x": -1, "y": -1, "parts": [ "frame_vertical", "halfboard_vertical" ] },
      { "x": -2, "y": 0, "parts": [ "frame_vertical", "cargo_space", "muffler" ] },
      { "x": -2, "y": 1, "parts": [ "frame_vertical", "cargo_space" ] },
      { "x": -2, "y": 2, "parts": [ "frame_vertical", "halfboard_vertical" ] },
      { "x": -2, "y": -1, "parts": [ "frame_vertical", "tank", "halfboard_vertical" ] },
      { "x": -3, "y": 0, "parts": [ "frame_vertical", "trunk", "muffler" ] },
      { "x": -3, "y": 1, "parts": [ "frame_vertical", "trunk" ] },
      { "x": -3, "y": 2, "parts": [ "frame_vertical", "halfboard_vertical" ] },
      { "x": -3, "y": -1, "parts": [ "frame_vertical", "halfboard_vertical" ] },
      { "x": -4, "y": 0, "parts": [ "frame_horizontal", "trunk" ] },
      { "x": -4, "y": 1, "parts": [ "frame_horizontal", "trunk" ] },
      { "x": -4, "y": 2, "parts": [ "frame_vertical", "wheel_mount_medium", "wheel", "halfboard_vertical" ] },
      { "x": -4, "y": -1, "parts": [ "frame_vertical", "wheel_mount_medium", "wheel", "halfboard_vertical" ] },
      { "x": -5, "y": 0, "parts": [ "frame_horizontal", "trunk" ] },
      { "x": -5, "y": 1, "parts": [ "frame_horizontal", "trunk" ] },
      { "x": -5, "y": 2, "parts": [ "frame_vertical", "halfboard_se" ] },
      { "x": -5, "y": -1, "parts": [ "frame_vertical", "halfboard_sw" ] }
    ],
    "items": [
      { "y": 0, "x": 0, "chance": 15, "item_groups": [ "car_misc" ] },
      { "y": 0, "x": 0, "chance": 10, "item_groups": [ "car_misc" ] },
      { "y": 1, "x": 0, "chance": 10, "item_groups": [ "car_misc" ] },
      { "y": 1, "x": 0, "chance": 5, "item_groups": [ "snacks" ] },
      { "y": 0, "x": 0, "chance": 5, "item_groups": [ "fast_food" ] },
      { "y": 0, "x": -2, "chance": 5, "item_groups": [ "farming_tools" ] },
      { "y": 1, "x": -2, "chance": 12, "item_groups": [ "car_kit" ] },
      { "y": 1, "x": -2, "chance": 12, "items": [ "jack", "wheel" ] },
      { "y": 1, "x": -3, "chance": 10, "item_groups": [ "car_kit" ] },
      { "y": 0, "x": -3, "chance": 8, "item_groups": [ "fuel_gasoline" ] },
      { "y": 1, "x": -2, "chance": 3, "items": [ "ax" ] }
    ]
  }
]
