[
  {
    "type": "recipe",
    "result": "gp5kit",
    "id_suffix": "uncraft",
    "category": "CC_OTHER",
    "subcategory": "CSC_OTHER_OTHER",
    "difficulty": 0,
    "time": "10 s",
    "reversible": true,
    "autolearn": true,
    "components": [
      [ [ "sm_filter_1a", 3 ] ],
      [ [ "mask_gp5", 1 ] ],
      [ [ "wrapped_rad_badge", 1 ] ],
      [ [ "mre_beef_box", 1 ] ],
      [ [ "pur_tablets", 15 ] ],
      [ [ "iodine", 15 ] ],
      [ [ "filter_bag", 1 ] ],
      [ [ "holdout_suit", 1 ] ]
    ]
  },
  {
    "type": "recipe",
    "result": "schm41_kit",
    "id_suffix": "uncraft",
    "category": "CC_OTHER",
    "subcategory": "CSC_OTHER_OTHER",
    "difficulty": 0,
    "time": "10 s",
    "reversible": true,
    "autolearn": true,
    "components": [
      [ [ "lg_filter", 2 ] ],
      [ [ "mask_hosed", 1 ] ],
      [ [ "wrapped_rad_badge", 1 ] ],
      [ [ "mre_beef_box", 1 ] ],
      [ [ "pur_tablets", 15 ] ],
      [ [ "iodine", 15 ] ],
      [ [ "large_filter_bag", 1 ] ],
      [ [ "heavy_filter_mod_b", 1 ] ],
      [ [ "ozk_suit", 1 ] ]
    ]
  },
  {
    "type": "recipe",
    "result": "fiberglass_disk",
    "category": "CC_OTHER",
    "subcategory": "CSC_OTHER_MATERIALS",
    "skill_used": "fabrication",
    "difficulty": 9,
    "time": "20 s",
    "reversible": false,
    "autolearn": false,
    "book_learn": [ [ "textbook_filters", 3 ] ],
    "qualities": [ { "id": "CHEM", "level": 1, "amount": 1 } ],
    "tools": [ [ [ "chemistry_set", 50 ] ], [ [ "toolset", 10 ] ] ],
    "components": [ [ [ "glass_shard", 15 ] ], [ [ "felt_patch", 5 ] ] ]
  },
  {
    "type": "recipe",
    "result": "cotton_filter",
    "category": "CC_OTHER",
    "subcategory": "CSC_OTHER_MATERIALS",
    "skill_used": "fabrication",
    "difficulty": 6,
    "time": "20 s",
    "reversible": false,
    "autolearn": false,
    "book_learn": [ [ "textbook_filters", 2 ] ],
    "qualities": [ { "id": "CHEM", "level": 1, "amount": 1 } ],
    "tools": [ [ [ "chemistry_set", 50 ] ], [ [ "toolset", 10 ] ] ],
    "components": [ [ [ "rag", 10 ] ], [ [ "disinfectant", 5 ] ], [ [ "ammonia", 5 ] ] ]
  },
  {
    "type": "recipe",
    "result": "act_charcoal",
    "category": "CC_OTHER",
    "subcategory": "CSC_OTHER_MATERIALS",
    "skill_used": "fabrication",
    "difficulty": 6,
    "time": "50 s",
    "reversible": false,
    "autolearn": false,
    "book_learn": [ [ "textbook_filters", 1 ] ],
    "qualities": [ { "id": "CHEM", "level": 2, "amount": 1 } ],
    "tools": [ [ [ "chemistry_set", 50 ] ], [ [ "toolset", 25 ] ], [ [ "char_kiln", -1 ] ] ],
    "components": [ [ [ "charcoal", 1 ] ], [ [ "chem_zinc_powder", 5 ] ], [ [ "scrap_copper", 1 ], [ "cable", 5 ] ] ]
  },
  {
    "type": "recipe",
    "result": "alum_grid",
    "category": "CC_OTHER",
    "subcategory": "CSC_OTHER_MATERIALS",
    "skill_used": "fabrication",
    "difficulty": 6,
    "time": "100 s",
    "reversible": false,
    "autolearn": false,
    "book_learn": [ [ "textbook_filters", 5 ] ],
    "qualities": [ { "id": "HAMMER", "level": 3, "amount": 1 } ],
    "tools": [
      [ [ "tongs", -1 ] ],
      [ [ "chisel", -1 ] ],
      [ [ "anvil", -1 ] ],
      [ [ "crucible", -1 ] ],
      [ [ "forge", 20 ], [ "char_forge", 4 ], [ "oxy_torch", 4 ] ]
    ],
    "components": [ [ [ "material_aluminium_ingot", 1 ], [ "can_drink", 8 ] ] ]
  },
  {
    "type": "recipe",
    "result": "filter_open_1",
    "id_suffix": "standard",
    "category": "CC_OTHER",
    "subcategory": "CSC_OTHER_MATERIALS",
    "difficulty": 6,
    "time": "100 s",
    "reversible": true,
    "autolearn": false,
    "book_learn": [ [ "textbook_filters", 6 ] ],
    "tools": [ [ [ "press", -1 ] ], [ [ "glasses_safety", -1 ] ], [ [ "mask_dust", -1 ] ] ],
    "components": [ [ [ "alum_grid", 2 ] ], [ [ "act_charcoal", 50 ] ], [ [ "cotton_filter", 1 ] ], [ [ "fiberglass_disk", 5 ] ] ]
  },
  {
    "type": "recipe",
    "result": "filter_open_2",
    "id_suffix": "standard",
    "category": "CC_OTHER",
    "subcategory": "CSC_OTHER_MATERIALS",
    "difficulty": 6,
    "time": "100 s",
    "reversible": true,
    "autolearn": false,
    "book_learn": [ [ "textbook_filters", 6 ] ],
    "tools": [ [ [ "press", -1 ] ], [ [ "glasses_safety", -1 ] ], [ [ "mask_dust", -1 ] ] ],
    "components": [ [ [ "alum_grid", 2 ] ], [ [ "act_charcoal", 50 ] ], [ [ "cotton_filter", 1 ] ], [ [ "fiberglass_disk", 5 ] ] ]
  },
  {
    "type": "recipe",
    "result": "maskcan_small",
    "category": "CC_OTHER",
    "subcategory": "CSC_OTHER_CONTAINERS",
    "skill_used": "fabrication",
    "difficulty": 6,
    "time": "100 s",
    "reversible": false,
    "autolearn": false,
    "book_learn": [ [ "textbook_filters", 4 ] ],
    "qualities": [ { "id": "HAMMER", "level": 3, "amount": 1 } ],
    "tools": [
      [ [ "tongs", -1 ] ],
      [ [ "chisel", -1 ] ],
      [ [ "anvil", -1 ] ],
      [ [ "crucible", -1 ] ],
      [ [ "forge", 20 ], [ "char_forge", 4 ], [ "oxy_torch", 4 ] ]
    ],
    "components": [ [ [ "can_food", 5 ], [ "steel_chunk", 1 ], [ "scrap", 3 ] ] ]
  },
  {
    "type": "recipe",
    "result": "maskcan_lg",
    "category": "CC_OTHER",
    "subcategory": "CSC_OTHER_CONTAINERS",
    "skill_used": "fabrication",
    "difficulty": 6,
    "time": "200 s",
    "reversible": false,
    "autolearn": false,
    "book_learn": [ [ "textbook_filters", 5 ] ],
    "qualities": [ { "id": "HAMMER", "level": 3, "amount": 1 } ],
    "tools": [
      [ [ "tongs", -1 ] ],
      [ [ "chisel", -1 ] ],
      [ [ "anvil", -1 ] ],
      [ [ "crucible", -1 ] ],
      [ [ "forge", 20 ], [ "char_forge", 4 ], [ "oxy_torch", 4 ] ]
    ],
    "components": [ [ [ "can_food", 10 ], [ "steel_chunk", 2 ], [ "scrap", 6 ] ] ]
  },
  {
    "type": "recipe",
    "result": "filtercap",
    "category": "CC_OTHER",
    "subcategory": "CSC_OTHER_MATERIALS",
    "skill_used": "fabrication",
    "difficulty": 2,
    "time": "100 s",
    "reversible": false,
    "autolearn": false,
    "book_learn": [ [ "textbook_filters", 1 ] ],
    "qualities": [ { "id": "HAMMER", "level": 3, "amount": 1 } ],
    "tools": [
      [ [ "tongs", -1 ] ],
      [ [ "chisel", -1 ] ],
      [ [ "anvil", -1 ] ],
      [ [ "swage", -1 ] ],
      [ [ "mold_plastic", -1 ] ],
      [ [ "forge", 50 ], [ "char_forge", 10 ], [ "oxy_torch", 10 ] ]
    ],
    "components": [ [ [ "plastic_chunk", 1 ] ], [ [ "steel_chunk", 1 ], [ "scrap", 3 ] ] ]
  },
  {
    "type": "recipe",
    "result": "filterplug",
    "category": "CC_OTHER",
    "subcategory": "CSC_OTHER_MATERIALS",
    "skill_used": "fabrication",
    "difficulty": 3,
    "time": "50 s",
    "reversible": false,
    "autolearn": false,
    "book_learn": [ [ "textbook_filters", 1 ] ],
    "tools": [ [ [ "mold_plastic", -1 ] ], [ [ "hotplate", 5 ], [ "toolset", 5 ], [ "surface_heat", 1, "LIST" ] ] ],
    "components": [ [ [ "plastic_chunk", 1 ] ] ]
  },
  {
    "type": "recipe",
    "result": "sm_filter_1a",
    "id_suffix": "uncraft",
    "category": "CC_OTHER",
    "subcategory": "CSC_OTHER_OTHER",
    "difficulty": 0,
    "time": "50 s",
    "reversible": false,
    "autolearn": false,
    "qualities": [ { "id": "SAW_M", "level": 1, "amount": 1 }, { "id": "HAMMER", "level": 1, "amount": 1 } ],
    "tools": [
      [ [ "tongs", -1 ] ],
      [ [ "hacksaw", -1 ] ],
      [ [ "hammer", -1 ] ],
      [ [ "glasses_safety", -1 ] ],
      [ [ "mask_dust", -1 ] ]
    ],
    "components": [
      [ [ "maskcan_small", 1 ] ],
      [ [ "rag", 5 ] ],
      [ [ "charcoal", 25 ] ],
      [ [ "alum_grid", 2 ] ],
      [ [ "fiberglass_disk", 5 ] ],
      [ [ "filtercap", 1 ] ],
      [ [ "filterplug", 1 ] ]
    ]
  },
  {
    "type": "recipe",
    "result": "sm_filter_1b",
    "id_suffix": "uncraft",
    "category": "CC_OTHER",
    "subcategory": "CSC_OTHER_OTHER",
    "difficulty": 0,
    "time": "50 s",
    "reversible": false,
    "autolearn": false,
    "qualities": [ { "id": "SAW_M", "level": 1, "amount": 1 }, { "id": "HAMMER", "level": 1, "amount": 1 } ],
    "tools": [
      [ [ "tongs", -1 ] ],
      [ [ "hacksaw", -1 ] ],
      [ [ "hammer", -1 ] ],
      [ [ "glasses_safety", -1 ] ],
      [ [ "mask_dust", -1 ] ]
    ],
    "components": [
      [ [ "maskcan_small", 1 ] ],
      [ [ "rag", 5 ] ],
      [ [ "charcoal", 25 ] ],
      [ [ "alum_grid", 2 ] ],
      [ [ "fiberglass_disk", 5 ] ],
      [ [ "filtercap", 1 ] ],
      [ [ "filterplug", 1 ] ]
    ]
  },
  {
    "type": "recipe",
    "result": "lg_filter",
    "id_suffix": "uncraft",
    "category": "CC_OTHER",
    "subcategory": "CSC_OTHER_OTHER",
    "difficulty": 0,
    "time": "50 s",
    "reversible": false,
    "autolearn": false,
    "qualities": [ { "id": "SAW_M", "level": 1, "amount": 1 }, { "id": "HAMMER", "level": 1, "amount": 1 } ],
    "tools": [
      [ [ "tongs", -1 ] ],
      [ [ "hacksaw", -1 ] ],
      [ [ "hammer", -1 ] ],
      [ [ "glasses_safety", -1 ] ],
      [ [ "mask_dust", -1 ] ]
    ],
    "components": [
      [ [ "maskcan_lg", 1 ] ],
      [ [ "rag", 25 ] ],
      [ [ "charcoal", 100 ] ],
      [ [ "alum_grid", 6 ] ],
      [ [ "fiberglass_disk", 15 ] ],
      [ [ "filtercap", 1 ] ],
      [ [ "filterplug", 1 ] ]
    ]
  },
  {
    "type": "recipe",
    "result": "cheek_filter",
    "category": "CC_OTHER",
    "subcategory": "CSC_OTHER_OTHER",
    "skill_used": "fabrication",
    "difficulty": 6,
    "time": "100 s",
    "reversible": false,
    "autolearn": false,
    "book_learn": [ [ "textbook_filters", 8 ] ],
    "qualities": [ { "id": "CHEM", "level": 2, "amount": 1 } ],
    "tools": [ [ [ "chemistry_set", 25 ] ], [ [ "toolset", 25 ] ], [ [ "hotplate", 10 ] ] ],
    "components": [ [ [ "plastic_chunk", 2 ] ], [ [ "act_charcoal", 100 ] ], [ [ "cotton_filter", 4 ] ], [ [ "bag_plastic", 1 ] ] ]
  },
  {
    "type": "recipe",
    "result": "mask_pbf_exp",
    "category": "CC_OTHER",
    "subcategory": "CSC_OTHER_OTHER",
    "skill_used": "fabrication",
    "difficulty": 0,
    "time": "1 s",
    "reversible": true,
    "autolearn": true,
    "components": [ [ [ "plastic_chunk", 2 ] ], [ [ "mask_pbf", 1 ] ] ]
  }
]
