[
  {
    "id": "arming_cap",
    "repairs_like": "balclava",
    "type": "ARMOR",
    "name": { "str": "arming cap" },
    "description": "A thick cap of quilted fabric, designed to be worn underneath mail or other armor.  Or worn on its own, if you can't afford proper armor.",
    "weight": "210 g",
    "volume": "250 ml",
    "price": "10 USD",
    "price_postapoc": "50 cent",
    "to_hit": -1,
    "bashing": 1,
    "material": [ "cotton" ],
    "symbol": "[",
    "looks_like": "balclava",
    "color": "green",
    "warmth": 30,
    "material_thickness": 5,
    "flags": [ "VARSIZE", "STURDY" ],
    "armor": { "coverage": 80, "covers": [ "head" ], "encumbrance": 15 }
  },
  {
    "id": "wood_helmet",
    "type": "ARMOR",
    "name": { "str": "wooden helmet" },
    "description": "a makeshift helmet carved out of a log with improvised padding",
    "weight": "800 g",
    "volume": "2000 ml",
    "price": "20 USD",
    "price_postapoc": "50 cent",
    "to_hit": -2,
    "bashing": 5,
    "material": [ "wood" ],
    "symbol": "[",
    "looks_like": "hat_hard",
    "color": "yellow",
    "warmth": 10,
    "material_thickness": 3,
    "environmental_protection": 1,
    "flags": [ "VARSIZE", "WATERPROOF" ],
    "armor": { "coverage": 90, "covers": [ "head" ], "encumbrance": 20 }
  }
]
