[
  {
    "id": "union_suit_faraday",
    "type": "ARMOR",
    "category": "armor",
    "name": { "str": "faraday union suit" },
    "description": "A union suit with copper wiring that can be worn under your normal clothing.  The suit is conductively interconnected, protecting against electricity.",
    "weight": "12000 g",
    "volume": "3000 ml",
    "price": "200 USD",
    "price_postapoc": "50 USD",
    "to_hit": -1,
    "material": [ "cotton", "copper" ],
    "symbol": "[",
    "color": "light_red",
    "covers": [ "torso", "head", "arm_l", "arm_r", "hand_l", "hand_r", "leg_l", "leg_r", "foot_l", "foot_r", "mouth", "eyes" ],
    "coverage": 100,
    "encumbrance": 10,
    "warmth": 15,
    "material_thickness": 0.2,
    "flags": [ "VARSIZE", "HELMET_COMPAT", "ELECTRIC_IMMUNE", "SKINTIGHT" ]
  }
]
