[
  {
    "id": "SRC_Case",
    "copy-from": "casing",
    "type": "GENERIC",
    "name": { "str": "M1926 SRC Casing" },
    "description": "An empty case for M1926 SRC rounds.",
    "weight": "6 g",
    "volume": "8 ml"
  },
  {
    "id": "SRC26",
    "type": "AMMO",
    "name": { "str": "M1926 SRC", "str_pl": "M1926 SRC" },
    "description": "Round(s) of M1926 Short Rifle Cartridge. Initially designed for the M1926 QFW, itself designed as a light support weapon, the round now sees service in the far superior SSRA.",
    "weight": "12 g",
    "volume": "250 ml",
    "price": "22 USD",
    "flags": [ "IRREPLACEABLE_CONSUMABLE" ],
    "material": [ "brass", "powder" ],
    "symbol": "=",
    "color": "yellow",
    "count": 40,
    "stack_size": 40,
    "ammo_type": "SRC",
    "casing": "SRC_Case",
    "range": 50,
    "damage": { "damage_type": "bullet", "amount": 45, "armor_penetration": 6 },
    "dispersion": 35,
    "recoil": 1500,
    "effects": [ "COOKOFF", "NEVER_MISFIRES" ]
  },
  {
    "id": "reloaded_SRC26",
    "copy-from": "SRC26",
    "type": "AMMO",
    "name": { "str": "reloaded M1926 SRC", "str_pl": "reloaded SRC" },
    "proportional": { "price": 0.7, "damage": { "damage_type": "bullet", "amount": 0.9 }, "dispersion": 1.1 },
    "extend": { "effects": [ "RECYCLED" ] },
    "delete": { "effects": [ "NEVER_MISFIRES" ], "flags": [ "IRREPLACEABLE_CONSUMABLE" ] }
  },
  {
    "id": "blackpowder_SRC26",
    "copy-from": "SRC26",
    "type": "AMMO",
    "name": { "str": "M1926 SRC, Reloaded, Blackpowder" },
    "proportional": {
      "price": 0.7,
      "damage": { "damage_type": "bullet", "amount": 0.76 },
      "recoil": 0.76,
      "armor_penetration": 0.5,
      "dispersion": 1.3
    },
    "extend": { "effects": [ "RECYCLED", "BLACKPOWDER", "MUZZLE_SMOKE" ] },
    "delete": { "effects": [ "NEVER_MISFIRES" ], "flags": [ "IRREPLACEABLE_CONSUMABLE" ] }
  },
  {
    "id": "BRC_Case",
    "type": "GENERIC",
    "category": "spare_parts",
    "name": { "str": "M1913 BRC Casing" },
    "description": "An empty case for M19 Basic Rifle Cartrages.",
    "weight": "10 g",
    "volume": "15ml",
    "stackable": true,
    "material": [ "brass" ],
    "symbol": "=",
    "color": "yellow",
    "damage_states": [ 0, 0 ]
  },
  {
    "id": "BRC_FMJ",
    "type": "AMMO",
    "name": { "str": "M1913 BRC" },
    "description": "The basic Rifle Cartrage was, due to measurement errors, one of the most powerful service rifle rounds of its era. On par with some(and sold as) big-game rounds, this thing will probally work fine for taking down a hard target or two.",
    "weight": "45 g",
    "volume": "25 ml",
    "price": "125 cent",
    "price_postapoc": "40 USD",
    "material": [ "brass", "powder" ],
    "symbol": "=",
    "color": "yellow",
    "count": 20,
    "stack_size": 20,
    "ammo_type": "BRC",
    "casing": "BRC_Case",
    "range": 55,
    "damage": { "damage_type": "bullet", "amount": 60, "armor_penetration": 12 },
    "dispersion": 25,
    "recoil": 5000,
    "flags": [ "IRREPLACEABLE_CONSUMABLE" ],
    "effects": [ "COOKOFF", "NEVER_MISFIRES" ]
  },
  {
    "id": "BRC_Reloaded",
    "copy-from": "BRC_FMJ",
    "type": "AMMO",
    "name": { "str": "Reloaded BRC round" },
    "proportional": { "price": 0.7, "damage": { "damage_type": "bullet", "amount": 0.9 }, "dispersion": 1.1 },
    "extend": { "effects": [ "RECYCLED" ] },
    "delete": { "effects": [ "NEVER_MISFIRES" ], "flags": [ "IRREPLACEABLE_CONSUMABLE" ] }
  },
  {
    "id": "BRC_Blackpowder",
    "copy-from": "BRC_FMJ",
    "type": "AMMO",
    "name": { "str": "Blackpowder BRC round" },
    "proportional": {
      "price": 0.7,
      "damage": { "damage_type": "bullet", "amount": 0.75 },
      "recoil": 0.76,
      "armor_penetration": 0.5,
      "dispersion": 1.3
    },
    "extend": { "effects": [ "RECYCLED", "BLACKPOWDER", "MUZZLE_SMOKE" ] },
    "delete": { "effects": [ "NEVER_MISFIRES" ], "flags": [ "IRREPLACEABLE_CONSUMABLE" ] }
  },
  {
    "id": "BRC_Match",
    "copy-from": "BRC_FMJ",
    "type": "AMMO",
    "name": { "str": "Match-loaded BRC round" },
    "description": "Carefully loaded rounds of M19 BRC, giving greater precision and reliability.",
    "proportional": { "dispersion": 0.75 },
    "delete": { "flags": [ "IRREPLACEABLE_CONSUMABLE" ] }
  },
  {
    "id": "BRC_Tracer",
    "copy-from": "BRC_FMJ",
    "type": "AMMO",
    "name": { "str": "BRC Tracer Ammunition" },
    "description": "Basic Rifle Cartrage rounds with a pyrotechnic compisition on the base, aiding the firer spot fall of shot. May also be used to set things on fire, but sadly unable to be reloaded.",
    "flags": [ "IRREPLACEABLE_CONSUMABLE" ],
    "proportional": { "price": 1.5 },
    "extend": { "effects": [ "INCENDIARY" ] }
  }
]
