[
  {
    "result": "m203_mod",
    "type": "recipe",
    "obsolete": true
  },
  {
    "result": "m320_mod_mod",
    "type": "recipe",
    "obsolete": true
  },
  {
    "result": "masterkey_mod",
    "type": "recipe",
    "obsolete": true
  },
  {
    "result": "rm121aux_mod",
    "type": "recipe",
    "obsolete": true
  },
  {
    "result": "u_shotgun_mod",
    "type": "recipe",
    "obsolete": true
  },
  {
    "result": "llink",
    "type": "recipe",
    "obsolete": true
  },
  {
    "result": "dias",
    "type": "recipe",
    "obsolete": true
  },
  {
    "result": "3006_clip",
    "type": "recipe",
    "obsolete": true
  },
  {
    "result": "762x39_clip",
    "type": "recipe",
    "obsolete": true
  },
  {
    "result": "762R_clip",
    "type": "recipe",
    "obsolete": true
  },
  {
    "result": "garandclip",
    "type": "recipe",
    "obsolete": true
  },
  {
    "result": "marlin_tubeloader",
    "type": "recipe",
    "obsolete": true
  },
  {
    "result": "survivor223mag",
    "type": "recipe",
    "obsolete": true
  },
  {
    "result": "ruger_makeshiftmag",
    "type": "recipe",
    "obsolete": true
  },
  {
    "result": "m14_makeshiftmag",
    "type": "recipe",
    "obsolete": true
  },
  {
    "result": "hk417_makeshiftmag",
    "type": "recipe",
    "obsolete": true
  },
  {
    "result": "ar10_makeshiftmag",
    "type": "recipe",
    "obsolete": true
  },
  {
    "result": "g3_makeshiftmag",
    "type": "recipe",
    "obsolete": true
  },
  {
    "result": "fal_makeshiftmag",
    "type": "recipe",
    "obsolete": true
  },
  {
    "result": "scarh_makeshiftmag",
    "type": "recipe",
    "obsolete": true
  },
  {
    "result": "scarh_makeshiftmag_conversion",
    "type": "recipe",
    "obsolete": true
  },
  {
    "result": "scarhmag",
    "type": "recipe",
    "obsolete": true
  },
  {
    "result": "scarhmag_30rd",
    "type": "recipe",
    "obsolete": true
  },
  {
    "result": "shotbelt_20",
    "type": "recipe",
    "obsolete": true
  },
  {
    "result": "smg_40_mag",
    "type": "recipe",
    "obsolete": true
  },
  {
    "result": "smg_45_mag",
    "type": "recipe",
    "obsolete": true
  },
  {
    "result": "ump45_makeshiftmag",
    "type": "recipe",
    "obsolete": true
  },
  {
    "result": "thompson_makeshiftmag",
    "type": "recipe",
    "obsolete": true
  },
  {
    "result": "survivor9mm_mag",
    "type": "recipe",
    "obsolete": true
  },
  {
    "result": "briefcase_smg",
    "type": "recipe",
    "obsolete": true
  },
  {
    "result": "pistol_flintlock",
    "type": "recipe",
    "obsolete": true
  },
  {
    "result": "rifle_flintlock",
    "type": "recipe",
    "obsolete": true
  },
  {
    "result": "carbine_flintlock",
    "type": "recipe",
    "obsolete": true
  },
  {
    "result": "carbine_flintlock_double",
    "type": "recipe",
    "obsolete": true
  },
  {
    "result": "carbine_flintlock_double_from_antiques",
    "type": "recipe",
    "obsolete": true
  },
  {
    "result": "revolver_shotgun",
    "type": "recipe",
    "obsolete": true
  },
  {
    "result": "surv_six_shooter",
    "type": "recipe",
    "obsolete": true
  },
  {
    "result": "surv_hand_cannon",
    "type": "recipe",
    "obsolete": true
  },
  {
    "result": "mosin91_30",
    "type": "recipe",
    "obsolete": true
  },
  {
    "result": "mosin44",
    "type": "recipe",
    "obsolete": true
  },
  {
    "result": "mosin91_30_ebr",
    "type": "recipe",
    "obsolete": true
  },
  {
    "result": "mosin44_ebr",
    "type": "recipe",
    "obsolete": true
  },
  {
    "result": "l_HFPack",
    "type": "recipe",
    "obsolete": true
  },
  {
    "result": "l_car_223",
    "type": "recipe",
    "obsolete": true
  },
  {
    "result": "l_mbr_223",
    "type": "recipe",
    "obsolete": true
  },
  {
    "result": "l_dsr_223",
    "type": "recipe",
    "obsolete": true
  },
  {
    "result": "l_lmg_223",
    "type": "recipe",
    "obsolete": true
  },
  {
    "result": "2_shot_special",
    "type": "recipe",
    "obsolete": true
  },
  {
    "result": "rifle_22",
    "type": "recipe",
    "obsolete": true
  },
  {
    "result": "pipe_shotgun",
    "type": "recipe",
    "obsolete": true
  },
  {
    "result": "pipe_double_shotgun",
    "type": "recipe",
    "obsolete": true
  },
  {
    "result": "pipe_combination_gun",
    "type": "recipe",
    "obsolete": true
  },
  {
    "result": "rifle_9mm",
    "type": "recipe",
    "obsolete": true
  },
  {
    "result": "rifle_308",
    "type": "recipe",
    "obsolete": true
  },
  {
    "result": "rifle_3006",
    "type": "recipe",
    "obsolete": true
  },
  {
    "result": "rifle_40",
    "type": "recipe",
    "obsolete": true
  },
  {
    "result": "rifle_9mm",
    "type": "recipe",
    "obsolete": true
  },
  {
    "result": "rifle_44",
    "type": "recipe",
    "obsolete": true
  },
  {
    "result": "rifle_45",
    "type": "recipe",
    "obsolete": true
  },
  {
    "result": "rifle_38",
    "type": "recipe",
    "obsolete": true
  },
  {
    "result": "rifle_308",
    "type": "recipe",
    "obsolete": true
  },
  {
    "result": "rifle_223",
    "type": "recipe",
    "obsolete": true
  },
  {
    "result": "surv_carbine_223",
    "type": "recipe",
    "obsolete": true
  },
  {
    "result": "rifle_3006",
    "type": "recipe",
    "obsolete": true
  },
  {
    "result": "triple_launcher_simple",
    "type": "recipe",
    "obsolete": true
  },
  {
    "result": "launcher_simple",
    "type": "recipe",
    "obsolete": true
  },
  {
    "result": "pipe_launcher40mm",
    "type": "recipe",
    "obsolete": true
  },
  {
    "result": "m320",
    "type": "recipe",
    "obsolete": true
  },
  {
    "result": "u_shotgun",
    "type": "recipe",
    "obsolete": true
  },
  {
    "result": "bigun",
    "type": "recipe",
    "obsolete": true
  },
  {
    "result": "ashot",
    "type": "recipe",
    "obsolete": true
  },
  {
    "result": "m2browning_sawn",
    "type": "recipe",
    "obsolete": true
  },
  {
    "result": "40x46mm_buckshot_m118",
    "type": "recipe",
    "obsolete": true
  },
  {
    "result": "40x46mm_buckshot_m199",
    "type": "recipe",
    "obsolete": true
  },
  {
    "result": "40x46mm_slug_m118",
    "type": "recipe",
    "obsolete": true
  },
  {
    "result": "40x46mm_slug_m199",
    "type": "recipe",
    "obsolete": true
  },
  {
    "result": "40x46mm_flechette_m118",
    "type": "recipe",
    "obsolete": true
  },
  {
    "result": "40x46mm_flechette_m199",
    "type": "recipe",
    "obsolete": true
  },
  {
    "result": "40x53mm_buckshot_m169",
    "type": "recipe",
    "obsolete": true
  },
  {
    "result": "40x53mm_slug_m169",
    "type": "recipe",
    "obsolete": true
  },
  {
    "result": "40x53mm_flechette_m169",
    "type": "recipe",
    "obsolete": true
  },
  {
    "result": "460_casing",
    "type": "recipe",
    "obsolete": true
  },
  {
    "result": "380_casing",
    "type": "recipe",
    "obsolete": true
  },
  {
    "result": "300blk_casing",
    "type": "recipe",
    "obsolete": true
  },
  {
    "result": "bp_9mm",
    "type": "recipe",
    "obsolete": true
  },
  {
    "result": "bp_9mmfmj",
    "type": "recipe",
    "obsolete": true
  },
  {
    "result": "bp_40sw",
    "type": "recipe",
    "obsolete": true
  },
  {
    "result": "bp_32_acp",
    "type": "recipe",
    "obsolete": true
  },
  {
    "result": "bp_38_fmj",
    "type": "recipe",
    "obsolete": true
  },
  {
    "result": "bp_45_acp",
    "type": "recipe",
    "obsolete": true
  },
  {
    "result": "bp_45_jhp",
    "type": "recipe",
    "obsolete": true
  },
  {
    "result": "bp_46mm",
    "type": "recipe",
    "obsolete": true
  },
  {
    "result": "bp_460_fmj",
    "type": "recipe",
    "obsolete": true
  },
  {
    "result": "bp_460_rowland",
    "type": "recipe",
    "obsolete": true
  },
  {
    "result": "bp_500_Magnum",
    "type": "recipe",
    "obsolete": true
  },
  {
    "result": "bp_762_25",
    "type": "recipe",
    "obsolete": true
  },
  {
    "result": "bp_9x18mm",
    "type": "recipe",
    "obsolete": true
  },
  {
    "result": "bp_9x18mmfmj",
    "type": "recipe",
    "obsolete": true
  },
  {
    "result": "bp_380_JHP",
    "type": "recipe",
    "obsolete": true
  },
  {
    "result": "bp_380_FMJ",
    "type": "recipe",
    "obsolete": true
  },
  {
    "result": "bp_57mm",
    "type": "recipe",
    "obsolete": true
  },
  {
    "result": "36navy",
    "type": "recipe",
    "obsolete": true
  },
  {
    "result": "44army",
    "type": "recipe",
    "obsolete": true
  },
  {
    "result": "reloaded_32_acp",
    "type": "recipe",
    "obsolete": true
  },
  {
    "result": "reloaded_38_fmj",
    "type": "recipe",
    "obsolete": true
  },
  {
    "result": "reloaded_38_special",
    "type": "recipe",
    "obsolete": true
  },
  {
    "result": "reloaded_38super_fmj",
    "type": "recipe",
    "obsolete": true
  },
  {
    "result": "reloaded_357sig_fmj",
    "type": "recipe",
    "obsolete": true
  },
  {
    "result": "reloaded_357sig_jhp",
    "type": "recipe",
    "obsolete": true
  },
  {
    "result": "reloaded_357mag_fmj",
    "type": "recipe",
    "obsolete": true
  },
  {
    "result": "reloaded_357mag_jhp",
    "type": "recipe",
    "obsolete": true
  },
  {
    "result": "bp_357mag_fmj",
    "type": "recipe",
    "obsolete": true
  },
  {
    "result": "bp_357mag_jhp",
    "type": "recipe",
    "obsolete": true
  },
  {
    "result": "bp_38_special",
    "type": "recipe",
    "obsolete": true
  },
  {
    "result": "reloaded_38_super",
    "type": "recipe",
    "obsolete": true
  },
  {
    "result": "reloaded_40fmj",
    "type": "recipe",
    "obsolete": true
  },
  {
    "result": "reloaded_40sw",
    "type": "recipe",
    "obsolete": true
  },
  {
    "result": "reloaded_10mm_fmj",
    "type": "recipe",
    "obsolete": true
  },
  {
    "result": "bp_10mm_fmj",
    "type": "recipe",
    "obsolete": true
  },
  {
    "result": "reloaded_44fmj",
    "type": "recipe",
    "obsolete": true
  },
  {
    "result": "reloaded_44magnum",
    "type": "recipe",
    "obsolete": true
  },
  {
    "result": "bp_44magnum",
    "type": "recipe",
    "obsolete": true
  },
  {
    "result": "bp_44fmj",
    "type": "recipe",
    "obsolete": true
  },
  {
    "result": "reloaded_45_acp",
    "type": "recipe",
    "obsolete": true
  },
  {
    "result": "reloaded_45_jhp",
    "type": "recipe",
    "obsolete": true
  },
  {
    "result": "reloaded_45_super",
    "type": "recipe",
    "obsolete": true
  },
  {
    "result": "reloaded_454_Casull",
    "type": "recipe",
    "obsolete": true
  },
  {
    "result": "bp_454_Casull",
    "type": "recipe",
    "obsolete": true
  },
  {
    "result": "reloaded_45colt_jhp",
    "type": "recipe",
    "obsolete": true
  },
  {
    "result": "reloaded_46mm",
    "type": "recipe",
    "obsolete": true
  },
  {
    "result": "reloaded_460_fmj",
    "type": "recipe",
    "obsolete": true
  },
  {
    "result": "reloaded_460_rowland",
    "type": "recipe",
    "obsolete": true
  },
  {
    "result": "reloaded_500_Magnum",
    "type": "recipe",
    "obsolete": true
  },
  {
    "result": "reloaded_57mm",
    "type": "recipe",
    "obsolete": true
  },
  {
    "result": "reloaded_762_25",
    "type": "recipe",
    "obsolete": true
  },
  {
    "result": "reloaded_9mm",
    "type": "recipe",
    "obsolete": true
  },
  {
    "result": "reloaded_9mmP",
    "type": "recipe",
    "obsolete": true
  },
  {
    "result": "reloaded_9mmP2",
    "type": "recipe",
    "obsolete": true
  },
  {
    "result": "reloaded_9mmfmj",
    "type": "recipe",
    "obsolete": true
  },
  {
    "result": "reloaded_9x18mm",
    "type": "recipe",
    "obsolete": true
  },
  {
    "result": "reloaded_9x18mmfmj",
    "type": "recipe",
    "obsolete": true
  },
  {
    "result": "reloaded_9x18mmP2",
    "type": "recipe",
    "obsolete": true
  },
  {
    "result": "reloaded_380_JHP",
    "type": "recipe",
    "obsolete": true
  },
  {
    "result": "reloaded_380_p",
    "type": "recipe",
    "obsolete": true
  },
  {
    "result": "reloaded_380_FMJ",
    "type": "recipe",
    "obsolete": true
  },
  {
    "result": "reloaded_22_fmj",
    "type": "recipe",
    "obsolete": true
  },
  {
    "result": "reloaded_22_lr",
    "type": "recipe",
    "obsolete": true
  },
  {
    "result": "bp_22_fmj",
    "type": "recipe",
    "obsolete": true
  },
  {
    "result": "bp_22_lr",
    "type": "recipe",
    "obsolete": true
  },
  {
    "result": "reloaded_223",
    "type": "recipe",
    "obsolete": true
  },
  {
    "result": "bp_223",
    "type": "recipe",
    "obsolete": true
  },
  {
    "result": "reloaded_270win_jsp",
    "type": "recipe",
    "obsolete": true
  },
  {
    "result": "bp_270win_jsp",
    "type": "recipe",
    "obsolete": true
  },
  {
    "result": "reloaded_300_winmag",
    "type": "recipe",
    "obsolete": true
  },
  {
    "result": "bp_300_winmag",
    "type": "recipe",
    "obsolete": true
  },
  {
    "result": "reloaded_3006",
    "type": "recipe",
    "obsolete": true
  },
  {
    "result": "reloaded_3006fmj",
    "type": "recipe",
    "obsolete": true
  },
  {
    "result": "reloaded_3006_incendiary",
    "type": "recipe",
    "obsolete": true
  },
  {
    "result": "bp_3006",
    "type": "recipe",
    "obsolete": true
  },
  {
    "result": "bp_3006fmj",
    "type": "recipe",
    "obsolete": true
  },
  {
    "result": "bp_3006_incendiary",
    "type": "recipe",
    "obsolete": true
  },
  {
    "result": "reloaded_308",
    "type": "recipe",
    "obsolete": true
  },
  {
    "result": "bp_308",
    "type": "recipe",
    "obsolete": true
  },
  {
    "result": "reloaded_4570_sp",
    "type": "recipe",
    "obsolete": true
  },
  {
    "result": "reloaded_4570_pen",
    "type": "recipe",
    "obsolete": true
  },
  {
    "result": "reloaded_4570_low",
    "type": "recipe",
    "obsolete": true
  },
  {
    "result": "reloaded_4570_bp",
    "type": "recipe",
    "obsolete": true
  },
  {
    "result": "reloaded_5x50dart",
    "type": "recipe",
    "obsolete": true
  },
  {
    "result": "reloaded_50bmg",
    "type": "recipe",
    "obsolete": true
  },
  {
    "result": "reloaded_50_incendiary",
    "type": "recipe",
    "obsolete": true
  },
  {
    "result": "reloaded_50ss",
    "type": "recipe",
    "obsolete": true
  },
  {
    "result": "reloaded_545",
    "type": "recipe",
    "obsolete": true
  },
  {
    "result": "reloaded_545_ap",
    "type": "recipe",
    "obsolete": true
  },
  {
    "result": "reloaded_300blk",
    "type": "recipe",
    "obsolete": true
  },
  {
    "result": "bp_300blk",
    "type": "recipe",
    "obsolete": true
  },
  {
    "result": "reloaded_556",
    "type": "recipe",
    "obsolete": true
  },
  {
    "result": "reloaded_556_incendiary",
    "type": "recipe",
    "obsolete": true
  },
  {
    "result": "bp_556",
    "type": "recipe",
    "obsolete": true
  },
  {
    "result": "bp_556_incendiary",
    "type": "recipe",
    "obsolete": true
  },
  {
    "result": "reloaded_700nx",
    "type": "recipe",
    "obsolete": true
  },
  {
    "result": "reloaded_762_51",
    "type": "recipe",
    "obsolete": true
  },
  {
    "result": "reloaded_762_51_incendiary",
    "type": "recipe",
    "obsolete": true
  },
  {
    "result": "bp_762_51",
    "type": "recipe",
    "obsolete": true
  },
  {
    "result": "bp_762_51_incendiary",
    "type": "recipe",
    "obsolete": true
  },
  {
    "result": "reloaded_762_54R",
    "type": "recipe",
    "obsolete": true
  },
  {
    "result": "reloaded_762_m43",
    "type": "recipe",
    "obsolete": true
  },
  {
    "result": "reloaded_762_m87",
    "type": "recipe",
    "obsolete": true
  },
  {
    "result": "40x46mm_buckshot_m118",
    "type": "recipe",
    "obsolete": true
  },
  {
    "result": "40x46mm_buckshot_m199",
    "type": "recipe",
    "obsolete": true
  },
  {
    "result": "40x46mm_slug_m118",
    "type": "recipe",
    "obsolete": true
  },
  {
    "result": "40x46mm_slug_m199",
    "type": "recipe",
    "obsolete": true
  },
  {
    "result": "40x46mm_flechette_m118",
    "type": "recipe",
    "obsolete": true
  },
  {
    "result": "40x46mm_flechette_m199",
    "type": "recipe",
    "obsolete": true
  },
  {
    "result": "40x53mm_buckshot_m169",
    "type": "recipe",
    "obsolete": true
  },
  {
    "result": "40x53mm_slug_m169",
    "type": "recipe",
    "obsolete": true
  },
  {
    "result": "40x53mm_flechette_m169",
    "type": "recipe",
    "obsolete": true
  },
  {
    "result": "shot_paper_00",
    "type": "recipe",
    "obsolete": true
  },
  {
    "result": "shot_paper_slug",
    "type": "recipe",
    "obsolete": true
  },
  {
    "result": "shot_paper_dragon",
    "type": "recipe",
    "obsolete": true
  },
  {
    "result": "shot_paper_bird",
    "type": "recipe",
    "obsolete": true
  },
  {
    "result": "bp_shot_bird",
    "type": "recipe",
    "obsolete": true
  },
  {
    "result": "bp_shot_00",
    "type": "recipe",
    "obsolete": true
  },
  {
    "result": "bp_shot_dragon",
    "type": "recipe",
    "obsolete": true
  },
  {
    "result": "bp_shot_slug",
    "type": "recipe",
    "obsolete": true
  },
  {
    "result": "bp_shot_flechette",
    "type": "recipe",
    "obsolete": true
  },
  {
    "result": "reloaded_shot_00",
    "type": "recipe",
    "obsolete": true
  },
  {
    "result": "reloaded_410shot_000",
    "type": "recipe",
    "obsolete": true
  },
  {
    "result": "reloaded_shot_bird",
    "type": "recipe",
    "obsolete": true
  },
  {
    "result": "reloaded_shot_dragon",
    "type": "recipe",
    "obsolete": true
  },
  {
    "result": "reloaded_shot_flechette",
    "type": "recipe",
    "obsolete": true
  },
  {
    "result": "reloaded_shot_slug",
    "type": "recipe",
    "obsolete": true
  },
  {
    "result": "bp_shot_00_with dowel",
    "type": "recipe",
    "obsolete": true
  },
  {
    "result": "bp_shot_bird_with dowel",
    "type": "recipe",
    "obsolete": true
  },
  {
    "result": "bp_shot_dragon_with dowel",
    "type": "recipe",
    "obsolete": true
  },
  {
    "result": "bp_shot_slug_with dowel",
    "type": "recipe",
    "obsolete": true
  },
  {
    "result": "bp_shot_flechette_with dowel",
    "type": "recipe",
    "obsolete": true
  },
  {
    "result": "bp_shot_scrap_with dowel",
    "type": "recipe",
    "obsolete": true
  },
  {
    "result": "bp_shot_scrap",
    "type": "recipe",
    "obsolete": true
  },
  {
    "result": "shot_scrap",
    "type": "recipe",
    "obsolete": true
  },
  {
    "result": "460_casing",
    "type": "recipe",
    "obsolete": true
  },
  {
    "result": "380_casing",
    "type": "recipe",
    "obsolete": true
  },
  {
    "result": "300blk_casing",
    "type": "recipe",
    "obsolete": true
  },
  {
    "result": "bp_9mm",
    "type": "recipe",
    "obsolete": true
  },
  {
    "result": "bp_9mmfmj",
    "type": "recipe",
    "obsolete": true
  },
  {
    "result": "bp_40fmj",
    "type": "recipe",
    "obsolete": true
  },
  {
    "result": "bp_40sw",
    "type": "recipe",
    "obsolete": true
  },
  {
    "result": "bp_32_acp",
    "type": "recipe",
    "obsolete": true
  },
  {
    "result": "bp_38_fmj",
    "type": "recipe",
    "obsolete": true
  },
  {
    "result": "bp_45_acp",
    "type": "recipe",
    "obsolete": true
  },
  {
    "result": "bp_45_jhp",
    "type": "recipe",
    "obsolete": true
  },
  {
    "result": "bp_46mm",
    "type": "recipe",
    "obsolete": true
  },
  {
    "result": "bp_460_fmj",
    "type": "recipe",
    "obsolete": true
  },
  {
    "result": "bp_460_rowland",
    "type": "recipe",
    "obsolete": true
  },
  {
    "result": "bp_500_Magnum",
    "type": "recipe",
    "obsolete": true
  },
  {
    "result": "bp_762_25",
    "type": "recipe",
    "obsolete": true
  },
  {
    "result": "bp_9x18mm",
    "type": "recipe",
    "obsolete": true
  },
  {
    "result": "bp_9x18mmfmj",
    "type": "recipe",
    "obsolete": true
  },
  {
    "result": "bp_380_JHP",
    "type": "recipe",
    "obsolete": true
  },
  {
    "result": "bp_380_FMJ",
    "type": "recipe",
    "obsolete": true
  },
  {
    "result": "bp_57mm",
    "type": "recipe",
    "obsolete": true
  },
  {
    "result": "36navy",
    "type": "recipe",
    "obsolete": true
  },
  {
    "result": "44army",
    "type": "recipe",
    "obsolete": true
  },
  {
    "result": "reloaded_32_acp",
    "type": "recipe",
    "obsolete": true
  },
  {
    "result": "reloaded_38_fmj",
    "type": "recipe",
    "obsolete": true
  },
  {
    "result": "reloaded_38_special",
    "type": "recipe",
    "obsolete": true
  },
  {
    "result": "reloaded_38super_fmj",
    "type": "recipe",
    "obsolete": true
  },
  {
    "result": "reloaded_357sig_fmj",
    "type": "recipe",
    "obsolete": true
  },
  {
    "result": "reloaded_357sig_jhp",
    "type": "recipe",
    "obsolete": true
  },
  {
    "result": "reloaded_357mag_fmj",
    "type": "recipe",
    "obsolete": true
  },
  {
    "result": "reloaded_357mag_jhp",
    "type": "recipe",
    "obsolete": true
  },
  {
    "result": "bp_357mag_fmj",
    "type": "recipe",
    "obsolete": true
  },
  {
    "result": "bp_357mag_jhp",
    "type": "recipe",
    "obsolete": true
  },
  {
    "result": "bp_38_special",
    "type": "recipe",
    "obsolete": true
  },
  {
    "result": "reloaded_38_super",
    "type": "recipe",
    "obsolete": true
  },
  {
    "result": "reloaded_40fmj",
    "type": "recipe",
    "obsolete": true
  },
  {
    "result": "reloaded_40sw",
    "type": "recipe",
    "obsolete": true
  },
  {
    "result": "reloaded_10mm_fmj",
    "type": "recipe",
    "obsolete": true
  },
  {
    "result": "bp_10mm_fmj",
    "type": "recipe",
    "obsolete": true
  },
  {
    "result": "reloaded_44fmj",
    "type": "recipe",
    "obsolete": true
  },
  {
    "result": "reloaded_44magnum",
    "type": "recipe",
    "obsolete": true
  },
  {
    "result": "bp_44magnum",
    "type": "recipe",
    "obsolete": true
  },
  {
    "result": "reloaded_45_acp",
    "type": "recipe",
    "obsolete": true
  },
  {
    "result": "reloaded_45_jhp",
    "type": "recipe",
    "obsolete": true
  },
  {
    "result": "reloaded_45_super",
    "type": "recipe",
    "obsolete": true
  },
  {
    "result": "reloaded_454_Casull",
    "type": "recipe",
    "obsolete": true
  },
  {
    "result": "bp_454_Casull",
    "type": "recipe",
    "obsolete": true
  },
  {
    "result": "reloaded_45colt_jhp",
    "type": "recipe",
    "obsolete": true
  },
  {
    "result": "reloaded_46mm",
    "type": "recipe",
    "obsolete": true
  },
  {
    "result": "reloaded_460_fmj",
    "type": "recipe",
    "obsolete": true
  },
  {
    "result": "reloaded_460_rowland",
    "type": "recipe",
    "obsolete": true
  },
  {
    "result": "reloaded_500_Magnum",
    "type": "recipe",
    "obsolete": true
  },
  {
    "result": "reloaded_57mm",
    "type": "recipe",
    "obsolete": true
  },
  {
    "result": "reloaded_762_25",
    "type": "recipe",
    "obsolete": true
  },
  {
    "result": "reloaded_9mm",
    "type": "recipe",
    "obsolete": true
  },
  {
    "result": "reloaded_9mmP",
    "type": "recipe",
    "obsolete": true
  },
  {
    "result": "reloaded_9mmP2",
    "type": "recipe",
    "obsolete": true
  },
  {
    "result": "reloaded_9mmfmj",
    "type": "recipe",
    "obsolete": true
  },
  {
    "result": "reloaded_9x18mm",
    "type": "recipe",
    "obsolete": true
  },
  {
    "result": "reloaded_9x18mmfmj",
    "type": "recipe",
    "obsolete": true
  },
  {
    "result": "reloaded_9x18mmP2",
    "type": "recipe",
    "obsolete": true
  },
  {
    "result": "reloaded_380_JHP",
    "type": "recipe",
    "obsolete": true
  },
  {
    "result": "reloaded_380_p",
    "type": "recipe",
    "obsolete": true
  },
  {
    "result": "reloaded_380_FMJ",
    "type": "recipe",
    "obsolete": true
  },
  {
    "result": "reloaded_22_fmj",
    "type": "recipe",
    "obsolete": true
  },
  {
    "result": "reloaded_22_lr",
    "type": "recipe",
    "obsolete": true
  },
  {
    "result": "bp_22_fmj",
    "type": "recipe",
    "obsolete": true
  },
  {
    "result": "bp_22_lr",
    "type": "recipe",
    "obsolete": true
  },
  {
    "result": "reloaded_223",
    "type": "recipe",
    "obsolete": true
  },
  {
    "result": "bp_223",
    "type": "recipe",
    "obsolete": true
  },
  {
    "result": "reloaded_270win_jsp",
    "type": "recipe",
    "obsolete": true
  },
  {
    "result": "bp_270win_jsp",
    "type": "recipe",
    "obsolete": true
  },
  {
    "result": "reloaded_300_winmag",
    "type": "recipe",
    "obsolete": true
  },
  {
    "result": "bp_300_winmag",
    "type": "recipe",
    "obsolete": true
  },
  {
    "result": "reloaded_3006",
    "type": "recipe",
    "obsolete": true
  },
  {
    "result": "reloaded_3006fmj",
    "type": "recipe",
    "obsolete": true
  },
  {
    "result": "reloaded_3006_incendiary",
    "type": "recipe",
    "obsolete": true
  },
  {
    "result": "bp_3006",
    "type": "recipe",
    "obsolete": true
  },
  {
    "result": "bp_3006fmj",
    "type": "recipe",
    "obsolete": true
  },
  {
    "result": "bp_3006_incendiary",
    "type": "recipe",
    "obsolete": true
  },
  {
    "result": "reloaded_308",
    "type": "recipe",
    "obsolete": true
  },
  {
    "result": "bp_308",
    "type": "recipe",
    "obsolete": true
  },
  {
    "result": "reloaded_4570_sp",
    "type": "recipe",
    "obsolete": true
  },
  {
    "result": "reloaded_4570_pen",
    "type": "recipe",
    "obsolete": true
  },
  {
    "result": "reloaded_4570_low",
    "type": "recipe",
    "obsolete": true
  },
  {
    "result": "reloaded_4570_bp",
    "type": "recipe",
    "obsolete": true
  },
  {
    "result": "reloaded_5x50dart",
    "type": "recipe",
    "obsolete": true
  },
  {
    "result": "reloaded_50bmg",
    "type": "recipe",
    "obsolete": true
  },
  {
    "result": "reloaded_50_incendiary",
    "type": "recipe",
    "obsolete": true
  },
  {
    "result": "reloaded_50ss",
    "type": "recipe",
    "obsolete": true
  },
  {
    "result": "reloaded_545",
    "type": "recipe",
    "obsolete": true
  },
  {
    "result": "reloaded_545_ap",
    "type": "recipe",
    "obsolete": true
  },
  {
    "result": "reloaded_300blk",
    "type": "recipe",
    "obsolete": true
  },
  {
    "result": "bp_300blk",
    "type": "recipe",
    "obsolete": true
  },
  {
    "result": "reloaded_556",
    "type": "recipe",
    "obsolete": true
  },
  {
    "result": "reloaded_556_incendiary",
    "type": "recipe",
    "obsolete": true
  },
  {
    "result": "bp_556",
    "type": "recipe",
    "obsolete": true
  },
  {
    "result": "bp_556_incendiary",
    "type": "recipe",
    "obsolete": true
  },
  {
    "result": "reloaded_700nx",
    "type": "recipe",
    "obsolete": true
  },
  {
    "result": "reloaded_762_51",
    "type": "recipe",
    "obsolete": true
  },
  {
    "result": "reloaded_762_51_incendiary",
    "type": "recipe",
    "obsolete": true
  },
  {
    "result": "bp_762_51",
    "type": "recipe",
    "obsolete": true
  },
  {
    "result": "bp_762_51_incendiary",
    "type": "recipe",
    "obsolete": true
  },
  {
    "result": "reloaded_762_54R",
    "type": "recipe",
    "obsolete": true
  },
  {
    "result": "reloaded_762_m43",
    "type": "recipe",
    "obsolete": true
  },
  {
    "result": "reloaded_762_m87",
    "type": "recipe",
    "obsolete": true
  },
  {
    "result": "36navy",
    "type": "recipe",
    "obsolete": true
  },
  {
    "result": "44army",
    "type": "recipe",
    "obsolete": true
  },
  {
    "result": "flintlock_ammo",
    "type": "recipe",
    "obsolete": true
  },
  {
    "result": "flintlock_shot",
    "type": "recipe",
    "obsolete": true
  },
  {
    "result": "bot_crows_m240",
    "type": "recipe",
    "obsolete": true
  }
]
