[
  {
    "id": "magical_min_water",
    "type": "COMESTIBLE",
    "comestible_type": "DRINK",
    "name": { "str": "Magical mineral water" },
    "description": "A glittering, dazzling shiny crystal clear bubbly water enriched with minerals...they say that it is even enchanted with some magical properties",
    "quench": 33,
    "healthy": 1,
    "calories": 0,
    "weight": "245 g",
    "volume": "275 ml",
    "price": "5 USD",
    "symbol": "~",
    "color": "light_cyan",
    "phase": "liquid",
    "container": "bottle_glass",
    "use_action": { "type": "cast_spell", "spell_id": "min_water_item_rejuv", "no_fail": true, "level": 0 }
  }
]
