    [
	  {
    "id": "power_armor_t51",
    "type": "ARMOR",
    "category": "armor",
    "name": "T-51 power armor",
    "description": "The T-51b powered infantry armor is designed with the latest passive defense features for both civilian and military disturbances. It requires power.",
    "weight": 20339,
    "volume": 100,
    "price": 7000000,
    "to_hit": 1,
    "bashing": 1,
    "material": [ "steel" ],
    "symbol": "[",
    "color": "light_gray",
    "covers": [ "TORSO", "ARMS", "HANDS", "LEGS", "FEET" ],
    "coverage": 100,
    "encumbrance": 30,
    "storage": 10,
    "warmth": 90,
    "power_armor": true,
    "material_thickness": 15,
    "environmental_protection": 15,
    "use_action": { "type": "ups_based_armor", "activate_msg": "Your power armor engages." },
    "flags": [ "WATERPROOF", "STURDY", "ELECTRIC_IMMUNE" ]
  },
  
    {
    "id": "power_armor_helmet_t51",
    "type": "ARMOR",
    "category": "armor",
    "name": "T-51b power helmet",
    "description": "A basic helmet, designed for use with the the T-51b Power Helmet.  Offers excellent protection from both attacks and environmental hazards.  Like all DoubleTech power armor, the control and climate-regulation systems require direct skin contact.",
    "weight": 3628,
    "volume": 20,
    "price": 2500000,
    "to_hit": 1,
    "bashing": 1,
    "material": [ "steel" ],
    "symbol": "[",
    "color": "light_gray",
    "covers": [ "HEAD", "EYES", "MOUTH" ],
    "coverage": 100,
    "encumbrance": 30,
    "warmth": 90,
    "power_armor": true,
    "material_thickness": 15,
    "environmental_protection": 15,
    "qualities": [ [ "GLARE", 2 ] ],
    "flags": [ "WATCH", "WATERPROOF", "STURDY", "PARTIAL_DEAF", "THERMOMETER", "SUN_GLASSES" ]
  },
  
    {
    "id": "power_armor_t45",
    "type": "ARMOR",
    "category": "armor",
    "name": "T-45 Power armor",
    "description": "A suit of T-45D power armor, T-51's weaker cousin, T-45 is bulky, but still effective.",
    "weight": 29009,
    "volume": 120,
    "price": 11500000,
    "to_hit": 1,
    "bashing": 1,
    "material": [ "hardsteel", "steel" ],
    "symbol": "[",
    "color": "dark_gray",
    "covers": [ "TORSO", "ARMS", "HANDS", "LEGS", "FEET" ],
    "coverage": 100,
    "encumbrance": 80,
    "storage": 16,
    "warmth": 60,
    "power_armor": true,
    "material_thickness": 10,
    "environmental_protection": 16,
    "use_action": { "type": "ups_based_armor", "activate_msg": "Your power armor engages." },
    "flags": [ "WATERPROOF", "STURDY", "ELECTRIC_IMMUNE" ]
  },
  
    {
    "id": "power_armor_helmet_t45",
    "type": "ARMOR",
    "category": "armor",
    "name": "T-45 power helmet",
    "description": "A T-45 power helmet. Bulky, but it works",
    "weight": 5442,
    "volume": 28,
    "price": 3750000,
    "to_hit": 1,
    "bashing": 1,
    "material": [ "hardsteel", "steel" ],
    "symbol": "[",
    "color": "dark_gray",
    "covers": [ "HEAD", "EYES", "MOUTH" ],
    "coverage": 100,
    "encumbrance": 80,
    "warmth": 60,
    "power_armor": true,
    "material_thickness": 10,
    "environmental_protection": 16,
    "qualities": [ [ "GLARE", 2 ] ],
    "flags": [ "WATCH", "WATERPROOF", "STURDY", "PARTIAL_DEAF", "THERMOMETER", "SUN_GLASSES" ]
  },
  
  	  {
    "id": "power_armor_x01",
    "type": "ARMOR",
    "category": "armor",
    "name": "Enclave X-01 Power Armor",
    "description": "One of the enclave's myriad of power armor models, the X-01 is the first model, used by the",
    "weight": 20339,
    "volume": 100,
    "price": 7000000,
    "to_hit": 1,
    "bashing": 1,
    "material": [ "ceramic", "superalloy" ],
    "symbol": "[",
    "color": "light_gray",
    "covers": [ "TORSO", "ARMS", "HANDS", "LEGS", "FEET" ],
    "coverage": 100,
    "encumbrance": 30,
    "storage": 10,
    "warmth": 90,
    "power_armor": true,
    "material_thickness": 15,
    "environmental_protection": 35,
    "use_action": { "type": "ups_based_armor", "activate_msg": "Your power armor engages." },
    "flags": [ "WATERPROOF", "STURDY", "ELECTRIC_IMMUNE" ]
  },
  
    {
    "id": "power_armor_helmet_x01",
    "type": "ARMOR",
    "category": "armor",
    "name": "enclave X-01 power helmet",
    "description": "An enclave power armor helmet. The eyes can have a menacing glow to them. The eye-glow is powered by conventional batteries.",
    "weight": 3628,
    "volume": 20,
    "price": 2500000,
    "to_hit": 1,
    "bashing": 1,
    "material": [ "ceramic", "superalloy" ],
    "symbol": "[",
    "color": "light_gray",
    "covers": [ "HEAD", "EYES", "MOUTH" ],
    "coverage": 100,
    "encumbrance": 30,
    "warmth": 90,
    "power_armor": true,
    "material_thickness": 15,
    "environmental_protection": 15,
    "qualities": [ [ "GLARE", 2 ] ],
	"ammo": "battery", 
	"charges_per_use": 1,
	    "use_action": {
      "type": "transform",
      "msg": "You turn the helmet on.",
      "target": "power_armor_helmet_x01_on",
      "active": true,
      "need_charges": 1,
      "need_charges_msg": "The helmet's batteries are dead."
    },
	    "magazines": [
      [
        "battery",
        [
          "light_battery_cell",
          "light_plus_battery_cell",
          "light_minus_battery_cell",
          "light_atomic_battery_cell",
          "light_minus_atomic_battery_cell",
          "light_minus_disposable_cell",
          "light_disposable_cell"
        ]
      ]
    ],
    "magazine_well": 1,
    "flags": [ "WATCH", "WATERPROOF", "STURDY", "PARTIAL_DEAF", "THERMOMETER", "SUN_GLASSES" ]
  },
  
	{
    "id": "power_armor_helmet_x01_on",
    "copy-from": "power_armor_helmet_x01",
    "repairs_like": "power_armor_helmet_x01",
    "type": "TOOL_ARMOR",
    "name": "enclave x-01 power armor helmet (on)",
    "name_plural": "enclave x-01 power armor helmets (on)",
    "description": "An Enclave Power Helmet, with the eyes glowing menacingly.",
    "flags": [ "LIGHT_450", "CHARGEDIM", "WATERPROOF", "TRADER_AVOID", "WATCH", "WATERPROOF", "STURDY", "PARTIAL_DEAF", "THERMOMETER", "SUN_GLASSES"  ],
    "power_draw": 15000,
    "revert_to": "power_armor_helmet_x01",
    "use_action": { "menu_text": "Turn off", "type": "transform", "msg": "The %s flicks off.", "target": "power_armor_helmet_x01" },
    "covers": [ "HEAD" ],
    "techniques": [ "WBLOCK_1" ],
    "magazine_well": 1
  }
	
	]
