[
  {
    "type": "uncraft",
    "result": "cob_weed_acdc",
    "activity_level": "LIGHT_EXERCISE",
    "time": "3 m",
    "//": "Break down dried buds into trimmed raw flower (no leaves) for rolling joints.",
    "qualities": [ { "id": "CUT", "level": 2 } ],
    "components": [ [ [ "cob_trimmed_acdc", 1 ] ] ]
  },
  {
    "type": "uncraft",
    "result": "cob_weed_cali_o",
    "activity_level": "LIGHT_EXERCISE",
    "time": "3 m",
    "//": "Break down dried buds into trimmed raw flower (no leaves) for rolling joints.",
    "qualities": [ { "id": "CUT", "level": 2 } ],
    "components": [ [ [ "cob_trimmed_cali_o", 1 ] ] ]
  },
  {
    "type": "uncraft",
    "result": "cob_weed_cannatonic",
    "activity_level": "LIGHT_EXERCISE",
    "time": "3 m",
    "//": "Break down dried buds into trimmed raw flower (no leaves) for rolling joints.",
    "qualities": [ { "id": "CUT", "level": 2 } ],
    "components": [ [ [ "cob_trimmed_cannatonic", 1 ] ] ]
  },
  {
    "type": "uncraft",
    "result": "cob_weed_cbd_critical_mass",
    "activity_level": "LIGHT_EXERCISE",
    "time": "3 m",
    "//": "Break down dried buds into trimmed raw flower (no leaves) for rolling joints.",
    "qualities": [ { "id": "CUT", "level": 2 } ],
    "components": [ [ [ "cob_trimmed_cbd_critical_mass", 1 ] ] ]
  },
  {
    "type": "uncraft",
    "result": "cob_weed_charlottes_web",
    "activity_level": "LIGHT_EXERCISE",
    "time": "3 m",
    "//": "Break down dried buds into trimmed raw flower (no leaves) for rolling joints.",
    "qualities": [ { "id": "CUT", "level": 2 } ],
    "components": [ [ [ "cob_trimmed_charlottes_web", 1 ] ] ]
  },
  {
    "type": "uncraft",
    "result": "cob_weed_dancehall",
    "activity_level": "LIGHT_EXERCISE",
    "time": "3 m",
    "//": "Break down dried buds into trimmed raw flower (no leaves) for rolling joints.",
    "qualities": [ { "id": "CUT", "level": 2 } ],
    "components": [ [ [ "cob_trimmed_dancehall", 1 ] ] ]
  },
  {
    "type": "uncraft",
    "result": "cob_weed_elektra",
    "activity_level": "LIGHT_EXERCISE",
    "time": "3 m",
    "//": "Break down dried buds into trimmed raw flower (no leaves) for rolling joints.",
    "qualities": [ { "id": "CUT", "level": 2 } ],
    "components": [ [ [ "cob_trimmed_elektra", 1 ] ] ]
  },
  {
    "type": "uncraft",
    "result": "cob_weed_gelato",
    "activity_level": "LIGHT_EXERCISE",
    "time": "3 m",
    "//": "Break down dried buds into trimmed raw flower (no leaves) for rolling joints.",
    "qualities": [ { "id": "CUT", "level": 2 } ],
    "components": [ [ [ "cob_trimmed_gelato", 1 ] ] ]
  },
  {
    "type": "uncraft",
    "result": "cob_weed_girl_scout_cookies",
    "activity_level": "LIGHT_EXERCISE",
    "time": "3 m",
    "//": "Break down dried buds into trimmed raw flower (no leaves) for rolling joints.",
    "qualities": [ { "id": "CUT", "level": 2 } ],
    "components": [ [ [ "cob_trimmed_girl_scout_cookies", 1 ] ] ]
  },
  {
    "type": "uncraft",
    "result": "cob_weed_gorilla_glue_4",
    "activity_level": "LIGHT_EXERCISE",
    "time": "3 m",
    "//": "Break down dried buds into trimmed raw flower (no leaves) for rolling joints.",
    "qualities": [ { "id": "CUT", "level": 2 } ],
    "components": [ [ [ "cob_trimmed_gorilla_glue_4", 1 ] ] ]
  },
  {
    "type": "uncraft",
    "result": "cob_weed_harle_tsu",
    "activity_level": "LIGHT_EXERCISE",
    "time": "3 m",
    "//": "Break down dried buds into trimmed raw flower (no leaves) for rolling joints.",
    "qualities": [ { "id": "CUT", "level": 2 } ],
    "components": [ [ [ "cob_trimmed_harle_tsu", 1 ] ] ]
  },
  {
    "type": "uncraft",
    "result": "cob_weed_harlequin",
    "activity_level": "LIGHT_EXERCISE",
    "time": "3 m",
    "//": "Break down dried buds into trimmed raw flower (no leaves) for rolling joints.",
    "qualities": [ { "id": "CUT", "level": 2 } ],
    "components": [ [ [ "cob_trimmed_harlequin", 1 ] ] ]
  },
  {
    "type": "uncraft",
    "result": "cob_weed_hawaiian_haze",
    "activity_level": "LIGHT_EXERCISE",
    "time": "3 m",
    "//": "Break down dried buds into trimmed raw flower (no leaves) for rolling joints.",
    "qualities": [ { "id": "CUT", "level": 2 } ],
    "components": [ [ [ "cob_trimmed_hawaiian_haze", 1 ] ] ]
  },
  {
    "type": "uncraft",
    "result": "cob_weed_jack_herer",
    "activity_level": "LIGHT_EXERCISE",
    "time": "3 m",
    "//": "Break down dried buds into trimmed raw flower (no leaves) for rolling joints.",
    "qualities": [ { "id": "CUT", "level": 2 } ],
    "components": [ [ [ "cob_trimmed_jack_herer", 1 ] ] ]
  },
  {
    "type": "uncraft",
    "result": "cob_weed_juanita_la_lagrimosa",
    "activity_level": "LIGHT_EXERCISE",
    "time": "3 m",
    "//": "Break down dried buds into trimmed raw flower (no leaves) for rolling joints.",
    "qualities": [ { "id": "CUT", "level": 2 } ],
    "components": [ [ [ "cob_trimmed_juanita_la_lagrimosa", 1 ] ] ]
  },
  {
    "type": "uncraft",
    "result": "cob_weed_lifter",
    "activity_level": "LIGHT_EXERCISE",
    "time": "3 m",
    "//": "Break down dried buds into trimmed raw flower (no leaves) for rolling joints.",
    "qualities": [ { "id": "CUT", "level": 2 } ],
    "components": [ [ [ "cob_trimmed_lifter", 1 ] ] ]
  },
  {
    "type": "uncraft",
    "result": "cob_weed_mango_haze",
    "activity_level": "LIGHT_EXERCISE",
    "time": "3 m",
    "//": "Break down dried buds into trimmed raw flower (no leaves) for rolling joints.",
    "qualities": [ { "id": "CUT", "level": 2 } ],
    "components": [ [ [ "cob_trimmed_mango_haze", 1 ] ] ]
  },
  {
    "type": "uncraft",
    "result": "cob_weed_northern_lights",
    "activity_level": "LIGHT_EXERCISE",
    "time": "3 m",
    "//": "Break down dried buds into trimmed raw flower (no leaves) for rolling joints.",
    "qualities": [ { "id": "CUT", "level": 2 } ],
    "components": [ [ [ "cob_trimmed_northern_lights", 1 ] ] ]
  },
  {
    "type": "uncraft",
    "result": "cob_weed_og_kush",
    "activity_level": "LIGHT_EXERCISE",
    "time": "3 m",
    "//": "Break down dried buds into trimmed raw flower (no leaves) for rolling joints.",
    "qualities": [ { "id": "CUT", "level": 2 } ],
    "components": [ [ [ "cob_trimmed_og_kush", 1 ] ] ]
  },
  {
    "type": "uncraft",
    "result": "cob_weed_pennywise",
    "activity_level": "LIGHT_EXERCISE",
    "time": "3 m",
    "//": "Break down dried buds into trimmed raw flower (no leaves) for rolling joints.",
    "qualities": [ { "id": "CUT", "level": 2 } ],
    "components": [ [ [ "cob_trimmed_pennywise", 1 ] ] ]
  },
  {
    "type": "uncraft",
    "result": "cob_weed_remedy",
    "activity_level": "LIGHT_EXERCISE",
    "time": "3 m",
    "//": "Break down dried buds into trimmed raw flower (no leaves) for rolling joints.",
    "qualities": [ { "id": "CUT", "level": 2 } ],
    "components": [ [ [ "cob_trimmed_remedy", 1 ] ] ]
  },
  {
    "type": "uncraft",
    "result": "cob_weed_ringos_gift",
    "activity_level": "LIGHT_EXERCISE",
    "time": "3 m",
    "//": "Break down dried buds into trimmed raw flower (no leaves) for rolling joints.",
    "qualities": [ { "id": "CUT", "level": 2 } ],
    "components": [ [ [ "cob_trimmed_ringos_gift", 1 ] ] ]
  },
  {
    "type": "uncraft",
    "result": "cob_weed_sour_diesel",
    "activity_level": "LIGHT_EXERCISE",
    "time": "3 m",
    "//": "Break down dried buds into trimmed raw flower (no leaves) for rolling joints.",
    "qualities": [ { "id": "CUT", "level": 2 } ],
    "components": [ [ [ "cob_trimmed_sour_diesel", 1 ] ] ]
  },
  {
    "type": "uncraft",
    "result": "cob_weed_sour_space_candy",
    "activity_level": "LIGHT_EXERCISE",
    "time": "3 m",
    "//": "Break down dried buds into trimmed raw flower (no leaves) for rolling joints.",
    "qualities": [ { "id": "CUT", "level": 2 } ],
    "components": [ [ [ "cob_trimmed_sour_space_candy", 1 ] ] ]
  },
  {
    "type": "uncraft",
    "result": "cob_weed_sour_tsunami",
    "activity_level": "LIGHT_EXERCISE",
    "time": "3 m",
    "//": "Break down dried buds into trimmed raw flower (no leaves) for rolling joints.",
    "qualities": [ { "id": "CUT", "level": 2 } ],
    "components": [ [ [ "cob_trimmed_sour_tsunami", 1 ] ] ]
  },
  {
    "type": "uncraft",
    "result": "cob_weed_special_sauce",
    "activity_level": "LIGHT_EXERCISE",
    "time": "3 m",
    "//": "Break down dried buds into trimmed raw flower (no leaves) for rolling joints.",
    "qualities": [ { "id": "CUT", "level": 2 } ],
    "components": [ [ [ "cob_trimmed_special_sauce", 1 ] ] ]
  },
  {
    "type": "uncraft",
    "result": "cob_weed_stardawg",
    "activity_level": "LIGHT_EXERCISE",
    "time": "3 m",
    "//": "Break down dried buds into trimmed raw flower (no leaves) for rolling joints.",
    "qualities": [ { "id": "CUT", "level": 2 } ],
    "components": [ [ [ "cob_trimmed_stardawg", 1 ] ] ]
  },
  {
    "type": "uncraft",
    "result": "cob_weed_strawberry_cough",
    "activity_level": "LIGHT_EXERCISE",
    "time": "3 m",
    "//": "Break down dried buds into trimmed raw flower (no leaves) for rolling joints.",
    "qualities": [ { "id": "CUT", "level": 2 } ],
    "components": [ [ [ "cob_trimmed_strawberry_cough", 1 ] ] ]
  },
  {
    "type": "uncraft",
    "result": "cob_weed_sweet_sour_widow",
    "activity_level": "LIGHT_EXERCISE",
    "time": "3 m",
    "//": "Break down dried buds into trimmed raw flower (no leaves) for rolling joints.",
    "qualities": [ { "id": "CUT", "level": 2 } ],
    "components": [ [ [ "cob_trimmed_sweet_sour_widow", 1 ] ] ]
  },
  {
    "type": "uncraft",
    "result": "cob_weed_trainwreck",
    "activity_level": "LIGHT_EXERCISE",
    "time": "3 m",
    "//": "Break down dried buds into trimmed raw flower (no leaves) for rolling joints.",
    "qualities": [ { "id": "CUT", "level": 2 } ],
    "components": [ [ [ "cob_trimmed_trainwreck", 1 ] ] ]
  },
  {
    "type": "uncraft",
    "result": "cob_weed_wedding_cake",
    "activity_level": "LIGHT_EXERCISE",
    "time": "3 m",
    "//": "Break down dried buds into trimmed raw flower (no leaves) for rolling joints.",
    "qualities": [ { "id": "CUT", "level": 2 } ],
    "components": [ [ [ "cob_trimmed_wedding_cake", 1 ] ] ]
  }
]
