[
  {
    "type": "mapgen",
    "om_terrain": "combogarageA_first",
    "method": "json",
    "object": {
      "fill_ter": "t_concrete_floor",
      "rows": [
        "###,,,,,,,,#############",
        "###,,,,,,,,#############",
        "###,,,,,,,,#############",
        "###,,,,,,,,#############",
        "###,,,,,,,,#############",
        "===        ====#########",
        "              =#########",
        "              =#########",
        "              =#########",
        "              =#########",
        "              =#########",
        "              =#########",
        "              =#########",
        "              =#########",
        "--------------=#########",
        "              =#########",
        "              =#########",
        "===============#########",
        "########################",
        "########################",
        "########################",
        "########################",
        "########################",
        "########################"
      ],
      "palettes": [ "multistory_house", "ground_level" ],
      "terrain": { " ": "t_concrete_floor", ",": "t_pavement" }
    }
  }
]
